{
    "id": 43,
    "singer_name": "秘密後院",
    "category": "华语组合/乐队",
    "singer_url": "https://music.163.com/artist?id=12263",
    "description": "卑微的唱道者涉世而來 不驚波瀾 不興水波 只唱些道心人情",
    "songs": [
        {
            "song_name": "送别",
            "song_url": "https://music.163.com/#//song?id=365639",
            "lyrics": "长亭外古道边\n芳草碧连天\n晚风拂柳笛声残\n夕阳山外山\n长亭外古道边\n芳草碧连天\n晚风拂柳笛声残\n夕阳山外山\n天之涯地之角\n知交半零落\n一壶浊酒尽余欢\n今宵别梦寒\n天之涯地之角\n知交半零落\n一壶浊酒尽余欢\n今宵别梦寒\n天之涯地之角\n知交半零落\n一壶浊酒尽余欢\n今宵别梦寒\n一壶浊酒尽余欢\n今宵别梦寒",
            "popularity": "3609",
            "time": "2012-05-25T00:00:00"
        },
        {
            "song_name": "竹叶舟",
            "song_url": "https://music.163.com/#//song?id=421563480",
            "lyrics": "摇啊摇\n过了烟波桥\n路迢迢\n心绪随风飘\n飘呀飘\n一叶逐浪摇\n思渺渺\n前程俱草草\n这浮浮沉沉的人间道\n谁把脚步走得太轻佻\n这风吹雨打的烟波桥\n谁在桥头漫说着逍遥\n向船艄\n一腔功名抛\n浪滔滔\n磨笔写前朝\n梦春宵\n二八佳人腰\n频频笑\n笑煞了渔樵\n长安道\n冷暖白衣薄\n枉费了\n青春正年少\n这跌跌撞撞的世嚣嚣\n谁在平底三尺做鹪鹩\n那山花山鸟的山阴道\n谁正一气纵横意翛翛\n这浮浮沉沉的人间道\n谁在平底三尺做鹪鹩\n这风吹雨打的烟波桥\n谁正一气纵横意翛翛\n摇啊摇\n竹叶舟飞棹\n飘呀飘\n人世这一遭\n飘呀飘\n人世这一遭",
            "popularity": "367",
            "time": "2016-07-19T00:00:00"
        },
        {
            "song_name": "两忘",
            "song_url": "https://music.163.com/#//song?id=365641",
            "lyrics": "但留弘一法，且去叔同名。\n山照山相见，水摇水中影。\n水上看山色，山间听水鸣。\n物我两忘后，一世好风景。\n但留弘一法，且去叔同名。\n山照山相见，水摇水中影。\n水上看山色，山间听水鸣。\n物我两忘后，一世好修行。\n我到为植种，我行花未开。\n念白：\n岂无佳色在，留待后人来。\n——注：念白为李叔同《咏菊》。",
            "popularity": "2421",
            "time": "2012-05-25T00:00:00"
        },
        {
            "song_name": "无言即是怀仙处",
            "song_url": "https://music.163.com/#//song?id=421423572",
            "lyrics": "",
            "popularity": "1096",
            "time": "2016-07-19T00:00:00"
        },
        {
            "song_name": "梦生",
            "song_url": "https://music.163.com/#//song?id=365687",
            "lyrics": "你的梦还是你的\n我的梦还是我的\n江湖的水啊，\n比梦更深\n相濡以沫的你啊\n是来日相忘的人\n山在转，水也在转\n低头见，抬头也见\n江湖的孩子\n江湖上漂\n目送飞鸿飞远\n手挥五弦，\n你看见，他也看见\n反反复复的恩怨\n与生俱来的纠缠\n梦醒的孩子\n睁开你的双眼\n静观花开花落\n云舒云卷\n青山在，绿水也在\n心已远，地自偏\n江湖的孩子\n江湖边老\n一曲晨钟悠然\n暮鼓悠然",
            "popularity": "1593",
            "time": "2012-12-01T00:00:00"
        },
        {
            "song_name": "梦",
            "song_url": "https://music.163.com/#//song?id=365629",
            "lyrics": "哀游子茕茕其无依兮，在天之涯。\n惟长夜漫漫而独寐兮，时恍惚以魂驰。\n梦偃卧摇篮以啼笑兮，似婴儿时。\n母食我甘酪与粉饵兮，父衣我以彩衣。\n月落乌啼，梦影依稀，往事知不知？\n汩半生哀乐之长逝兮，感亲之恩其永垂。\n哀游子怆怆而自怜兮， 吊形影悲。\n惟长夜漫漫而独寐兮， 时恍惚以魂驰。\n梦挥泪出门辞父母兮， 叹生别离。\n父语我眠食宜珍重兮， 母语我以早归。\n月落乌啼，梦影依稀， 往事知不知？\n汩半生哀乐之长逝兮， 感亲之恩其永垂。\n月落乌啼，梦影依稀， 往事知不知？\n汩半生哀乐之长逝兮， 感亲之恩其永垂。\n汩半生哀乐之长逝兮， 感亲之恩其永垂。",
            "popularity": "2332",
            "time": "2012-05-25T00:00:00"
        },
        {
            "song_name": "桑田",
            "song_url": "https://music.163.com/#//song?id=39224810",
            "lyrics": "两耳不闻\n一心一弦\n青山遮住\n毕竟东还\n斗转斗转\n当天少年\n一心一意\n自理桑田\n此心此弦\n春风几度\n数暖数寒\n岁岁华年\n方寸之间\n滄海桑田",
            "popularity": "134",
            "time": "2015-12-17T00:00:00"
        },
        {
            "song_name": "春景",
            "song_url": "https://music.163.com/#//song?id=365627",
            "lyrics": "南园春半踏青时\n风和闻马嘶\n青梅如豆柳如眉\n日长蝴蝶飞\n花露重\n草烟低\n人家帘幕垂\n秋千慵困解罗衣\n画梁双燕归\n南园春半踏青时\n风和闻马嘶\n青梅如豆柳如眉\n日长蝴蝶飞\n花露重\n草烟低\n人家帘幕垂\n秋千慵困解罗衣\n画梁双燕归\n花露重\n草烟低\n人家帘幕垂\n秋千慵困解罗衣\n画梁双燕归\n秋千慵困解罗衣\n画梁双燕归",
            "popularity": "105",
            "time": "2012-05-25T00:00:00"
        },
        {
            "song_name": "白云中",
            "song_url": "https://music.163.com/#//song?id=421423584",
            "lyrics": "酷爱无人境\n高飞出鸟笼\n吟诗闲度日\n观化静临风\n酷爱无人境\n高飞出鸟笼\n吟诗闲度日\n观化静临风\n杖策南山北\n酣歌西阪东\n红尘多少事\n不到白云中\n酷爱无人境\n高飞出鸟笼\n吟诗闲度日\n观化静临风\n杖策南山北\n酣歌西阪东\n红尘多少事\n不到白云中\n杖策南山北\n酣歌西阪东\n红尘多少事\n不到白云中\n红尘多少事\n不到白云中",
            "popularity": "401",
            "time": "2016-07-19T00:00:00"
        },
        {
            "song_name": "忆儿时",
            "song_url": "https://music.163.com/#//song?id=365623",
            "lyrics": "......\n春去秋来\n岁月如流\n游子伤漂泊\n回忆儿时\n家居嬉戏\n光景宛如昨\n......\n春去秋来\n岁月如流\n游子伤漂泊\n回忆儿时\n家居嬉戏\n光景宛如昨\n茅屋三椽\n老梅一树\n树底迷藏捉\n高枝啼鸟\n小川游鱼\n曾把闲情托\n......\n茅屋三椽\n老梅一树\n树底迷藏捉\n高枝啼鸟\n小川游鱼\n曾把闲情托\n茅屋三椽\n老梅一树\n树底迷藏捉\n高枝啼鸟\n小川游鱼\n曾把闲情托\n高枝啼鸟\n小川游鱼\n曾把闲情托\n儿时欢乐\n儿时欢乐\n斯乐不可作",
            "popularity": "671",
            "time": "2012-05-25T00:00:00"
        },
        {
            "song_name": "春去秋来",
            "song_url": "https://music.163.com/#//song?id=39224820",
            "lyrics": "春天的你\n秋天的你\n春秋一去\n数不清的你\n开颜的你\n锁眉的你\n悲喜交集\n你往哪儿去\n春已去了\n秋天也去了\n春去秋来\n你在哪儿呢\n悲喜去了\n你我也去了\n人潮汹涌\n其犹孤旅者呦\n其犹孤旅者哟",
            "popularity": "154",
            "time": "2015-12-17T00:00:00"
        },
        {
            "song_name": "弟子归",
            "song_url": "https://music.163.com/#//song?id=28029261",
            "lyrics": "父母呼 應勿緩 父母命 行勿懶 父母教 須敬聽 父母責 須善應\n冬則溫 夏則凊 晨則省 昏則定 出必告 反必面 居有常 業無變\n當時年紀小，當時樂陶陶\n不知憂不知苦，滿山遍野跑\n母親將言傳，父親以身教\n有志不怕年少，莫謂時日早\n事雖小 勿妄為 苟妄為 子道虧 物雖小 勿私藏 苟私藏 親心傷\n親所好 力為具 親所惡 謹為去 身有傷 貽親憂 德有傷 貽親羞\n一天又一天，天下都走遍\n冷暖人世間，回頭有溫暖\n當時方年少，當時樂逍遙\n青絲變白髮，辛苦才知道\n青絲變白髮，辛苦才知道\n親愛我 孝何難 親憎我 孝方賢 親有過 諫使更 怡吾色 柔吾聲\n諫不入 悅複諫 善巧勸 終無怨 親有疾 藥先嘗 晝夜侍 不離床\n春秋物化冉，聚散人世間\n你走遠他走遠，誰在雙親邊\n誰在雙親邊，殷殷持孝感\n父母在不遠遊，弟子當知返\n春秋物化冉，聚散人世間\n你走遠他走遠，誰在雙親邊\n誰在雙親邊，殷殷持孝感\n父母在不遠遊，弟子當知返\n喪三年 常悲咽 居處變 酒肉絕 喪盡禮 祭盡诚 事死者 如事生",
            "popularity": "401",
            "time": "2013-11-30T00:00:00"
        },
        {
            "song_name": "晨钟",
            "song_url": "https://music.163.com/#//song?id=365667",
            "lyrics": "晓风宿醉\n搵游子泪\n杨柳岸\n江湖边\n满楼红袖展\n天涯路远\n日暮乡关\n落日意\n游子情\n萧萧班马鸣\n半世情由不明\n一生风波未定\n一晌贪欢初醒\n此身虽在堪惊\n蒓鲈味\n胡不归\n晨钟悠然独醉\n晓风宿醉\n搵游子泪\n杨柳岸\n江湖边\n满楼红袖展\n天涯路远\n日暮乡关\n落日意\n游子情\n萧萧班马鸣\n半世情由不明\n一生风波未定\n一晌贪欢初醒\n此身虽在堪惊\n蒓鲈味\n胡不归\n晨钟悠然独醉\n悠然独醉\n悠然独醉",
            "popularity": "650",
            "time": "2012-12-01T00:00:00"
        },
        {
            "song_name": "历尘",
            "song_url": "https://music.163.com/#//song?id=421563479",
            "lyrics": "我见世间人\n生而还复死\n昨朝犹二八\n壮气胸襟士\n如今七十多\n力困形憔悴\n恰似春日花\n朝开夜落尔\n朝开夜落尔\n如一羽空中\n逐年月西东\n赶晨昏何事兴冲冲\n抬眼问苍穹\n低眉论穷通\n失来去浮生又匆匆\n天涯的风啊\n像你的白发\n静悄悄寂寞的挣扎\n赤手搏年华\n只身渡水崖\n羡渔樵纵浪在大化\n分清浊踪浪在大化\n游物外云水绕仙乡\n旧山河平平常常\n故人家凄凄凉凉\n唱道情惊醒了时光\n旧山河平平常常\n故人家凄凄凉凉\n唱道情惊醒了时光\n旧山河平平常常\n故人家凄凄凉凉\n唱道情惊醒了时光\n唱道情惊醒了时光",
            "popularity": "468",
            "time": "2016-07-19T00:00:00"
        },
        {
            "song_name": "凤兮",
            "song_url": "https://music.163.com/#//song?id=39227775",
            "lyrics": " 作曲 : 匡笑余\n凤兮凤兮\n何如德之衰也\n来世不可待\n往世不可追也\n凤兮凤兮\n何如德之衰也\n来世不可待\n往世不可追也\n凤兮凤兮\n何如德之衰也\n来世不可待\n往世不可追也\n凤兮凤兮\n何如德之衰也\n来世不可待\n往世不可追也\n凤兮凤兮\n何如德之衰也\n来世不可待\n往世不可追也",
            "popularity": "519",
            "time": "2015-12-17T00:00:00"
        },
        {
            "song_name": "逢渠桥",
            "song_url": "https://music.163.com/#//song?id=1472794194",
            "lyrics": " 作词 : 匡笑余\n 作曲 : 匡笑余\n 词曲/吉他/采样：匡笑余\n 三弦/吉他：邹广超\n 口琴/女声：贩贩\n 男声合声：哓哓\n 鼓/录制：阿星\n 编曲：秘密后院\n 密林间的香火 默照无常的世间\n 逢渠桥上的故人 一转身已越千年\n 渠今不是我 我今又是谁呢\n 渠今又是谁 谁又是谁呢\n 风雨潇潇如当年 子规声声又缠绵\n 与渠相契的桥头 结满世代的乡愁\n 渠今正是我 我今又是谁呀\n 我今不是渠 渠又是谁呀\n 渠今正是我 我今又是谁呀\n 我今不是渠 渠又是谁呀\n 当年人向当年去 此间客借此间老\n 谁把一庵月静静看了 谁化漫天晚霞照古道\n 当年人向当年去 此间客借此间老\n 谁把一庵月静静看了 谁化漫天晚霞照古道\n 当年人向当年去 此间客借此间老\n 当年人 当年去 此间客 此间老",
            "popularity": "92",
            "time": "2020-09-03T00:00:00"
        },
        {
            "song_name": "黍离",
            "song_url": "https://music.163.com/#//song?id=39224815",
            "lyrics": "彼黍离离，彼稷之苗。\n行迈靡靡，中心摇摇。\n知我者谓我心忧，\n不知我者谓我何求。\n彼黍離離，彼稷之穗。\n行迈靡靡，中心如醉。\n知我者谓我心忧，\n不知我者谓我何求。\n彼黍离离，彼稷之实。\n行迈靡靡，中心如噎。\n知我者谓我心忧，\n不知我者谓我何求。\n知我者谓我心忧，\n不知我者谓我何求。\n悠悠苍天，此何人哉！",
            "popularity": "1250",
            "time": "2015-12-17T00:00:00"
        },
        {
            "song_name": "诸真歌颂",
            "song_url": "https://music.163.com/#//song?id=421563482",
            "lyrics": "昔涉玄真道，腾步登太霞。\n负笈造天关，借问太上家。\n寂通寄兴感，玄气摄动音。\n高轮虽参差，万仞故来寻。\n鼓檝乘神波，稽首希晨风。\n未获解脱期，逍遥丘林中。\n林室有逸欢，绝此轩外交。\n遗景附圆曜，嘉音何寥寥。\n嘉音何寥寥。\n寥寥。",
            "popularity": "45",
            "time": "2016-07-19T00:00:00"
        },
        {
            "song_name": "浮生六记",
            "song_url": "https://music.163.com/#//song?id=1478184572",
            "lyrics": " 作词 : 沈复\n 作曲 : 匡笑余\n 改编自“清”沈复《浮生六记·卷六·养生记道》\n 世事茫茫\n 算而今何必奔忙\n 人生碌碌\n 费思想竞短论长\n 得失难量\n 夸哪般夜月乌江\n 宫冷台荒\n 富贵草头霜\n 余与琢堂冒雪登焉\n 俯视长空\n 琼花飞舞\n 遥指银山玉树\n 恍如身在瑶台\n 江中往来小艇\n 纵横掀播\n 如浪卷残叶\n 名利之心至此一冷\n 龙楼凤阁\n 说什么利锁名缰\n 闲来静处\n 且将诗酒猖狂\n 且将诗酒猖狂\n 唱一曲归来未晚\n 歌一调湖海茫茫\n 约几个知心密友\n 到野外溪旁\n 看花枝堆锦绣\n 听鸟语弄笙簧\n 一任他人情反复\n 世态炎凉\n 一任他人情反复\n 世态炎凉\n 优游闲岁月\n 潇洒度时光\n 优游闲岁月\n 潇洒度时光\n 优游闲岁月\n 潇洒度时光\n 优游闲岁月\n 潇洒度时光\n 是夜月色颇佳\n 俯视河中\n 波光如练\n 轻罗小扇\n 仰见飞云过天\n 变态万状\n 人生坎坷\n 何为乎来哉\n 往往皆自作孽耳",
            "popularity": "84",
            "time": "2020-09-24T00:00:00"
        },
        {
            "song_name": "秋夜",
            "song_url": "https://music.163.com/#//song?id=365624",
            "lyrics": "眉月一弯夜三更\n画屏深处宝鸭篆烟青\n唧唧唧唧 唧唧唧唧\n秋虫绕砌鸣\n小簟凉多睡味清\nEND",
            "popularity": "209",
            "time": "2012-05-25T00:00:00"
        },
        {
            "song_name": "伤春",
            "song_url": "https://music.163.com/#//song?id=365635",
            "lyrics": "看落花飘，听杜鹃叫，一片片是惊报，一声声是警告。\n看落花飘，听杜鹃叫，似劝说觉悟呀！青春易老。\n人生过隙驹，今日朱颜，明日憔悴。\n人生过隙驹，今日繁华明日非。\n花落人怜，人死谁悲？花落人埋，人死谁瘗？\n歎落红之漂泊，感人生之须臾。\n看落花飘，听杜鹃叫，一片片是惊报，一声声是警告。\n看落花飘，听杜鹃叫，似劝说觉悟呀！青春易老。\n人生过隙驹，今日朱颜，明日憔悴。\n人生过隙驹，今日繁华明日非。\n花落人怜，人死谁悲？花落人埋，人死谁瘗？\n歎落红之漂泊，感人生之须臾。\n看落花飘，听杜鹃叫，一片片是惊报，一声声是警告。\n看落花飘，听杜鹃叫，似劝说觉悟呀！青春易老。\n人生过隙驹，今日朱颜，明日憔悴。\n人生过隙驹，青春一去徒伤悲。",
            "popularity": "183",
            "time": "2012-05-25T00:00:00"
        },
        {
            "song_name": "春游",
            "song_url": "https://music.163.com/#//song?id=365637",
            "lyrics": "春风吹面薄于纱春人妆束淡于画\n游春人在画中行万花飞舞春人下\n梨花淡白菜花黄柳花委地芥花香\n莺啼陌上人归去花外疏钟送夕阳\n春风吹面薄于纱春人妆束淡于画\n游春人在画中行万花飞舞春人下\n梨花淡白菜花黄柳花委地芥花香\n莺啼陌上人归去花外疏钟送夕阳\n梨花淡白菜花黄柳花委地芥花香\n莺啼陌上人归去花外疏钟送夕阳\n莺啼陌上人归去花外疏钟送夕阳",
            "popularity": "139",
            "time": "2012-05-25T00:00:00"
        },
        {
            "song_name": "早秋",
            "song_url": "https://music.163.com/#//song?id=365625",
            "lyrics": " 作词 : 李叔同\n 作曲 : 李叔同\n十裡明湖一叶舟\n十裡明湖一叶舟\n城南烟月水西楼\n几许秋容娇欲流\n隔着垂杨柳\n远山明淨眉尖瘦\n闲云飘忽罗纹绉\n天末凉风送早秋\n秋花点点头\n十裡明湖一叶舟\n城南烟月水西楼\n几许秋容娇欲流\n隔着垂杨柳\n远山明淨眉尖瘦\n闲云飘忽罗纹绉\n天末凉风送早秋\n秋花点点头\n秋花点点头\n秋花点点头\n秋花点点头",
            "popularity": "155",
            "time": "2012-05-25T00:00:00"
        },
        {
            "song_name": "大遊仙（早春首发版）",
            "song_url": "https://music.163.com/#//song?id=459791294",
            "lyrics": " 作词 : 文康\n 作曲 : 匡笑余\n锦样年华水样过，轮蹄风雨暗消磨。\n仓皇一枕黄粱梦，都付人间春梦婆。\n（念白）：小子风尘奔走，不道姓名。\n只因作了半世懵懂痴人，醒来一场繁华大梦，\n思之无味，说也可怜。\n随口编了几句道情，无非唤醒痴聋，破除烦恼。\n这也叫做「只得如此，无可奈何」。\n不免将来请教诸公，聊当一笑。\n鼓逢逢，第一声，\n莫争喧，仔细听，\n人生世上浑如梦。\n春花秋月消磨尽，苍狗白云变态中。\n游丝万丈飘无定。\n诌几句盲词瞎话，当做他暮鼓晨钟。\n判官家，说帝王，征诛惨，揖让忙，\n暴秦炎汉糊涂账。\n六朝金粉空尘迹，五代干戈小戏场。\n李唐赵宋风吹浪。\n抵多少寺僧白雁，都成了纸上文章！\n最难逃，名利关，拥铜山，铁券传，\n丰碑早见磨刀惨。\n驮来薏苡冤难雪，击碎珊瑚酒未寒。\n千秋最苦英雄汉。\n早知道三分鼎足，尽痴心六出祁山！\n怎如他，耕织图，一张机，一把锄，\n两般便是擎天柱。\n春祈秋报香三炷，饮蜡歙豳酒半壶。\n儿童闹击迎年鼓。\n一家儿呵呵大笑，都说道「完了官租」！\n尽逍遥，渔伴樵，靠青山，傍水坳，\n手竿肩担明残照。\n网来肥鳜擂姜煮，砍得青松带叶烧。\n衔杯敢把王侯笑。\n醉来时狂歌一曲，猛抬头月小天高。\n猛抬头月小天高。\n牧童儿，自在身，走横桥，卧树荫，\n短蓑斜笠相厮趁。\n夕阳鞭影垂杨外，春雨笛声红杏林。\n世间最好骑牛稳。\n日西矬归家晚饭，稻粥香扑鼻啧啧。\n羡高风，隐逸流，住深山，怕出头，\n山中乐事般般有。\n闲招猿鹤成三友，坐拥诗书傲五侯。\n云多不碍梅花瘦。\n浑不问眼前兴废，再休提皮里春秋！\n破愁城，酒一杯，觅当垆，酤旧醅，\n酒徒夺尽人间萃。\n卦中奇耦闲休问，叶底枯荣任几回。\n倾囊拼作千场醉。\n不怕你天惊石破，怎当他酣睡如雷！\n老头陀，好快哉，鬓如霜，貌似孩，\n削光头发须眉在。\n菩提了悟原非树，明镜空悬哪是台？\n蛤蜊到口心无碍。\n俺只管薅锄烦恼，没来由见甚如来！\n学神仙，作道家，踏芒鞋，绾髻丫，\n葫芦一个斜肩挂。\n丹头不卖房中药，指上休谈顷刻花。\n随缘便是长生法。\n听说他结茅云外，却叫人何处寻他？\n鼓声敲，敲渐低，曲将终，鼓瑟希，\n西风紧吹啼猿起。\n《阳关三叠》伤心调，杜老《七哀》写怨诗。\n此中无限英雄泪。\n收拾起浮生闲话，交还他鼓板新词！\n（念白）：这番闲话君听者，不是闲饶舌。\n飞鸟各投林，残照吞明灭。\n俺则待唱着这道情儿，归山去也！",
            "popularity": "226",
            "time": "2017-02-13T00:00:00"
        },
        {
            "song_name": "林下",
            "song_url": "https://music.163.com/#//song?id=1486917621",
            "lyrics": " 作词 : 匡笑余\n 作曲 : 匡笑余\n 词曲/吉他/采样：匡笑余\n 秦琴：邹广超\n 箫：哓哓\n 木鱼：贩贩\n 鼓/小打/录制：阿星\n 编曲：秘密后院\n 林下凉亭 默坐孤僧\n 水鸭欢腾 静中何闻\n 空舟池塘 云水他乡\n 风荷摇荡 灿烂悠扬\n 谁夜来再把吴钩暗赏\n 辜负了平生救世心肠\n 夜雨把蚊虫惊惶共赴沙场\n 化众生又来在佛前奔忙\n 林下往事 风过耳旁\n 水鸭欢唱 一时两忘\n 空舟遗岸 故人还乡\n 风荷摇荡 灿烂苍茫\n 谁夜来再把吴钩暗赏\n 辜负了平生救世心肠\n 夜雨把蚊虫惊惶共赴沙场\n 化众生又来在佛前奔忙\n 谁夜来再把吴钩暗赏\n 辜负了平生救世心肠\n 夜雨把蚊虫惊惶共赴沙场\n 化众生又来在佛前奔忙\n 化众生又来在佛前奔忙",
            "popularity": "59",
            "time": "2020-10-28T00:00:00"
        },
        {
            "song_name": "归隐",
            "song_url": "https://music.163.com/#//song?id=421423574",
            "lyrics": "愁闻剑戟扶危主\n闷听笙歌聒醉人\n携取旧书归旧隐\n野花啼鸟一般春\n十年踪迹走红尘\n回首青山入梦频\n紫绶纵荣争及睡\n朱门虽贵不如贫\n愁闻剑戟扶危主\n闷听笙歌聒醉人\n携取旧书归旧隐\n野花啼鸟一般春\n十年踪迹走红尘\n回首青山入梦频\n紫绶纵荣争及睡\n朱门虽贵不如贫\n愁闻剑戟扶危主\n闷听笙歌聒醉人\n携取旧书归旧隐\n野花啼鸟一般春\n愁闻剑戟扶危主\n闷听笙歌聒醉人\n携取旧书归旧隐\n野花啼鸟一般春\n携取旧书归旧隐\n野花啼鸟一般春",
            "popularity": "106",
            "time": "2016-07-19T00:00:00"
        },
        {
            "song_name": "留别",
            "song_url": "https://music.163.com/#//song?id=365622",
            "lyrics": "满斟绿醑留君住\n莫匆匆归去\n三分春色二分愁\n更一分风雨\n花开花谢 都来几许\n且高歌休诉\n不知来岁牡丹时\n再相逢何处\n满斟绿醑留君住\n莫匆匆归去\n三分春色二分愁\n更一分风雨\n满斟绿醑留君住\n莫匆匆归去\n三分春色二分愁\n更一分风雨\n花开花谢 都来几许\n且高歌休诉\n不知来岁牡丹时\n再相逢何处\n花开花谢 都来几许\n且高歌休诉\n不知来岁牡丹时\n再相逢何处\n不知来岁牡丹时\n再相逢何处",
            "popularity": "205",
            "time": "2012-05-25T00:00:00"
        },
        {
            "song_name": "灰飞",
            "song_url": "https://music.163.com/#//song?id=365678",
            "lyrics": "雨雪霏霏\n昔我来归\n春风少年郎\n独步江湖上\n春风少年郎\n独步江湖上\n雨雪霏霏\n今我又归\n极目色苍苍\n人事两非非\n雨雪霏霏\n今我不归\n烟水两茫茫\n杯酒何彷徨\n雨雪霏霏\n今我化灰\n生老死寂灭\n洒然一捧灰",
            "popularity": "508",
            "time": "2012-12-01T00:00:00"
        },
        {
            "song_name": "月殇",
            "song_url": "https://music.163.com/#//song?id=39224818",
            "lyrics": "词／曲：匡笑余\n空负月华如水\n未洗却尘世的悲\n谁于飘渺的云上\n闲看人间的痴妄\n轻送年华如羽\n裹挟奔流的你\n一脚踏空的欢愉\n转身百年的惋惜\n只身茫茫人海\n独木撑持摇摆\n风口浪尖的生涯\n起落沉浮见真假\n未洗却心头污秽\n谁借朗月清晖\n照此身是非累累\n看此身是非累累",
            "popularity": "178",
            "time": "2015-12-17T00:00:00"
        },
        {
            "song_name": "无根树",
            "song_url": "https://music.163.com/#//song?id=39224814",
            "lyrics": "词／曲：匡笑余\n被风吹着走\n从少年到白头\n一生就像一条路\n路上没有你要的归宿\n雨丝如鞭打\n追逐向天涯\n一生就像一首歌\n歌里没有你要的解脱\n無根樹\n花正孤\n叹迷途\n太模糊\n风吹烟花散\n酒肉心头淡\n一生就像一条船\n回头才是岸\n雨打荣华休\n天地入扁舟\n一生就像一江水\n桥流人不流\n花正無\n無名姓\n返太無",
            "popularity": "135",
            "time": "2015-12-17T00:00:00"
        },
        {
            "song_name": "忆江南",
            "song_url": "https://music.163.com/#//song?id=421423573",
            "lyrics": "沉醉处\n缥缈玉京山\n唱彻步虚清燕罢\n不知今夕是何年\n唱彻步虚清燕罢\n不知今夕是何年\n唱彻步虚清燕罢\n不知今夕是何年\n唱彻步虚清燕罢\n不知今夕是何年\n海水又桑田",
            "popularity": "93",
            "time": "2016-07-19T00:00:00"
        },
        {
            "song_name": "归雁",
            "song_url": "https://music.163.com/#//song?id=365633",
            "lyrics": "不如归去归故山\n故山隐约苍漫漫\n几日东风过寒食\n秋来花事已阑珊。\n疏林寂寂双燕飞，\n低徊软语语呢喃。\n呢喃，呢喃，呢喃，呢喃，\n雕梁春去梦如烟，\n绿芜庭院罢歌弦，\n乌衣门巷捐秋扇，\n树杪斜阳淡欲眠，\n天涯芳草离亭晚，\n不如归去归故山，\n故山隐约苍漫漫。\n雕梁春去梦如烟，\n绿芜庭院罢歌弦，\n乌衣门巷捐秋扇，\n树杪斜阳淡欲眠，\n天涯芳草离亭晚，\n不如归去归故山，\n故山隐约苍漫漫。\n几日东风过寒食，\n秋来花事已阑珊。\n疏林寂寂双燕飞，\n低徊软语语呢喃。\n雕梁春去梦如烟，\n绿芜庭院罢歌弦，\n乌衣门巷捐秋扇，\n树杪斜阳淡欲眠，\n天涯芳草离亭晚，\n呢喃，呢喃，呢喃，呢喃，\n不如归去归故山。",
            "popularity": "191",
            "time": "2012-05-25T00:00:00"
        },
        {
            "song_name": "叶落",
            "song_url": "https://music.163.com/#//song?id=365672",
            "lyrics": "蒙胧胧的晚钟\n灰蒙蒙的时空\n依旧年华似水声\n轻飘飘地相送\n轰隆隆的一生\n升沉不过又秋风\n无边落叶萧萧下\n峰回路转旧天涯\n回旋何须恋风尘\n黄泉深处故人家\n蒙胧胧的晚钟\n灰蒙蒙的时空\n依旧年华似水声\n轻飘飘地相送\n轰隆隆的一生\n升沉不过又秋风\n无边落叶萧萧下\n峰回路转旧天涯\n回旋何须恋风尘\n黄泉深处故人家",
            "popularity": "302",
            "time": "2012-12-01T00:00:00"
        },
        {
            "song_name": "殿前欢",
            "song_url": "https://music.163.com/#//song?id=421563484",
            "lyrics": "醉颜酡，醒来徐步杖藜拖。\n家童伴我池塘坐，鸥鹭清波。\n映水红莲五六科，秋光过，两句新题破。\n秋霜残菊，夜雨枯荷。\n醉颜酡，水边林下且婆娑。\n醉时拍手随腔和，一曲狂歌。\n除渔樵那两个，无灾祸，此一着谁参破？\n南柯梦绕，梦绕南柯。\n醉颜酡，前贤不醉我今何？\n古来已错今犹错，世事从他。\n楚三闾葬汨罗，名犹播，谁在高唐卧？\n巫娥梦我，我梦巫娥。\n醉颜酡，云娘行酒雪儿歌。\n醉时吟狂时舞醒时坐。不醉如何？\n得快活且快活。今日个，只得随缘过。\n恋眼前富贵，看门外风波。\n恋眼前富贵，看门外风波。",
            "popularity": "231",
            "time": "2016-07-19T00:00:00"
        },
        {
            "song_name": "念此际",
            "song_url": "https://music.163.com/#//song?id=1474423519",
            "lyrics": "",
            "popularity": "17",
            "time": "2020-09-10T00:00:00"
        },
        {
            "song_name": "皈依",
            "song_url": "https://music.163.com/#//song?id=365791",
            "lyrics": " 作词 : 秘密後院\n 作曲 : 秘密後院\n作曲 : 秘密后院\n作词 : 秘密后院\n收拾起大地\n山河一担装\n满足四大皆空相\n勘破了世情\n生死两茫茫\n跌落莲台作宝相\n放下了来去\n爱恨的家当\n普度众生为谁忙\n参透是非前\n真假虚空相\n苦海无边的迷茫\n折一段枯叶残荷\n权当作衣裳\n打扮起五色五识眼耳盲\n一般芸芸众生相\n准备好来世简单的行囊\n也是匆匆轮回忙\n折一段枯叶残荷\n权当作衣裳\n你说皈要怎样才是皈\n你说依要怎样才是依\n还不是想这样\n还不是想那样\n还不是厌倦了流浪\n你说皈要怎样才是皈\n你说依要怎样才算依\n还不是想这样\n还不是想那样\n还不是厌倦了流浪\n还不是想这样\n还不是想那样\n还不是厌倦了流浪",
            "popularity": "175",
            "time": "2006-06-01T00:00:00"
        },
        {
            "song_name": "空城计",
            "song_url": "https://music.163.com/#//song?id=39227780",
            "lyrics": " 作词 : 匡笑余\n 作曲 : 匡笑余\n月是当年\n高懸人間\n有时繁华有时凌乱\n照城中流年\n別時依依\n聚时惜惜\n一时人来一时人去\n一城悲欢遍地\n谁在城上唱一出空城的计\n谁在城外笑看这岁月的戏\n风起云涌\n悲欢情动\n喜怒哀乐忧思惊恐\n空空一城如梦\n流水今日\n明月前身\n刹那风波风沙都无声\n流浪生死凡尘\n年华几许\n人间继续\n一树落花流水的记忆\n谁把人生如戏\n戏中谁在唱这出空城的计\n风流云散\n一别如雨\n谁在城上唱这出空城的计\n风雨情浓\n人間情重\n一缕残魂飘摇入怀中\n演这空城一梦",
            "popularity": "152",
            "time": "2015-12-17T00:00:00"
        },
        {
            "song_name": "三梦歌",
            "song_url": "https://music.163.com/#//song?id=421423575",
            "lyrics": "三梦歌\n一枕梦黄粱\n邯郸道路长\n梦断熟黄粱\n叹息能几长\n往事南柯梦\n荣华富贵多\n谁信是南柯\n叹息能几何\n叹息能几何\n蝶绕庄周梦\n逍遥物外游\n蝴蝶绕庄周\n叹息能几秋\n蝴蝶绕庄周\n叹息能几秋\n锦样年华水样过\n轮蹄风雨暗消磨\n仓皇一枕黄粱梦\n都付人间春梦婆\n都付人间春梦婆",
            "popularity": "111",
            "time": "2016-07-19T00:00:00"
        },
        {
            "song_name": "一刹",
            "song_url": "https://music.163.com/#//song?id=421563483",
            "lyrics": "漠漠苍生\n历历人烟\n沧海与桑田荡漾在一水间\n沧海与桑田荡漾在一水间\n寂寂此心\n烈烈飞焰\n动静之间坐看水火的缠绵\n动静之间坐看水火的缠绵\n与人间草木\n结永世的流连\n红尘为泥化一壶水木的变迁\n红尘为泥化一壶水木的变迁\n消息盈虚\n生生不息\n造化天地间正灰飞 正相见\n造化天地间正灰飞 正相见\n白云黄鹤道人家\n一琴一剑一杯茶\n羽衣常带烟霞色\n不染人间桃李花\n不染人间桃李花",
            "popularity": "69",
            "time": "2016-07-19T00:00:00"
        },
        {
            "song_name": "逍遙遊",
            "song_url": "https://music.163.com/#//song?id=1494259738",
            "lyrics": " 作词 : 莊子\n 作曲 : 匡笑余\n【战国】庄子《逍遥游》\n藐姑射之山\n有神人居焉\n肌肤若冰雪\n淖约若处子\n不食五谷\n吸风饮露\n乘云气\n御飞龙\n而游乎四海之外\n藐姑射之山\n有神人居焉\n肌肤若冰雪\n淖约若处子\n不食五谷\n吸风饮露\n乘云气\n御飞龙\n而游乎四海之外\n其神凝\n使物不疵疠而年榖熟\n乘云气\n御飞龙\n而游乎四海之外\n其神凝\n使物不疵疠而年榖熟\n而年榖熟",
            "popularity": "15",
            "time": "2018-02-03T00:00:00"
        },
        {
            "song_name": "幽居",
            "song_url": "https://music.163.com/#//song?id=365631",
            "lyrics": "",
            "popularity": "204",
            "time": "2012-05-25T00:00:00"
        },
        {
            "song_name": "洞山联句",
            "song_url": "https://music.163.com/#//song?id=1811984839",
            "lyrics": " 作词 : 匡笑余/洞山良价/南怀瑾\n 作曲 : 匡笑余\n 词：洞山良价/南怀瑾/匡笑余\n 曲/吉他/采样/唱：匡笑余\n 秦琴/吉他：邹广超\n 风琴/口琴：贩贩\n 箫/帮腔：哓哓\n 唱偈：延融师\n 小打/录制：阿星\n 编曲：秘密后院\n 净洗浓妆为阿谁\n 子规声里劝人归\n 百花落尽啼无尽\n 更向乱峰深处啼\n \u001f——洞山良价\n 道业名山不费寻\n 天人三界有声闻\n 夜来再把吴钩看\n 辜负平生救世心\n 道业名山不费寻\n 天人三界有声闻\n 夜来再把吴钩看\n 辜负平生救世心\n 道业名山不费寻\n 天人三界有声闻\n 夜来再把吴钩看\n 辜负平生救世心\n ——南怀瑾\n 惯听山雨抱蝉鸣\n 抛却红尘一片心\n 结夏云水远人境\n 始信江湖别有情\n 惯听山雨抱蝉鸣\n 抛却红尘一片心\n 结夏云水远人境\n 始信江湖别有情\n ——匡笑余",
            "popularity": "28",
            "time": "2021-01-28T00:00:00"
        },
        {
            "song_name": "沧海",
            "song_url": "https://music.163.com/#//song?id=39224819",
            "lyrics": "我慢慢地走过了所有地方\n回首烽烟散尽\n我慢慢地看过了所有的你\n触目悲喜分明\n我慢慢地演过了所有的戏\n如舟梦中穿行\n我慢慢地唱过了所有的歌\n此后万缘俱寂\n我慢慢地阖上了千山万水\n独向云深处去\n我慢慢地分割下一方沧海\n独木支我天地\n我慢慢地听过了所有的诗\n此生尘埃落定\n我慢慢地关上了所有的窗\n此生如梦初醒\n初醒",
            "popularity": "486",
            "time": "2015-12-17T00:00:00"
        },
        {
            "song_name": "阮郎归",
            "song_url": "https://music.163.com/#//song?id=421563478",
            "lyrics": "炎天何处可登临。须于物外寻。\n松风涧水杂清音。空山如弄琴。\n宜散发，称披襟。都无烦暑侵。\n莫将城市比山林。山林兴味深。\n豪家大厦敞千楹。风摇玉柄轻。\n金盆弄水复敲冰。热从何处生。\n低草舍，小茅亭。如何安此身。\n元来一念静无尘。萧然心自清。\n金乌玉兔最无情。驱驰不暂停。\n春光才去又朱明。年华只暗惊。\n须省悟，莫劳神。朱颜不再新。\n灭除妄想养天真。管无寒暑侵。\n谁言无处避炎光。山中有草堂。\n安然一枕即仙乡。竹风穿户凉。\n名不恋，利都忘。心闲日自长。\n不须辛苦觅琼浆。华池神水香。\n炎炎皦日正当中。澄潭忽此逢。\n金丹乍浴表深功。通明照水红。\n丹浴罢，乐无穷。怡然百体融。\n人间何处不清风。此怀谁与同。\n寒来暑往几时休。光阴逐水流。\n浮云身世两悠悠。何劳身外求。\n天上月，水边楼。须将一醉酬。\n陶然无喜亦无忧。人生且自由。\n人生且自由。\n人生且自由。",
            "popularity": "133",
            "time": "2016-07-19T00:00:00"
        },
        {
            "song_name": "清明",
            "song_url": "https://music.163.com/#//song?id=28029265",
            "lyrics": "清明故事长\n人在青烟上\n一脉心香悠悠转\n都在方寸间\n故人踪影茫\n行人又断肠\n一抔尘土风云散\n故事谁讲完\n谁抖落手中的线\n让一世一世血脉相连\n谁看见谁又看不见\n这一张一张黄色的脸\n清明故事长\n人在青烟上\n一脉心香悠悠转\n都在方寸间\n故人踪影茫\n行人又断肠\n一抔尘土风云散\n故事谁讲完\n谁抖落手中的线\n让一世一世血脉相连\n谁看见谁又看不见\n这一张一张黄色的脸\n谁划断绵延的线\n任一寸一寸飞絮散乱\n谁遗忘谁在尘世间\n这一张一张黄色的脸\n谁遗忘谁在尘世间\n这一张一张黄色的脸",
            "popularity": "470",
            "time": "2013-11-30T00:00:00"
        },
        {
            "song_name": "王维的树",
            "song_url": "https://music.163.com/#//song?id=1956215190",
            "lyrics": " 作词 : 匡笑余\n 作曲 : 匡笑余\n 词/曲/吉他/主唱：匡笑余\n 吉他：邹广超\n 箫：哓哓\n 鼓/和声：志明\n 小打：阿星\n 编曲：秘密后院\n 录音/后期/母带处理：阿星\n 录音室：广州低音量工作室\n 封面书法：玄同\n 封面设计：贩贩\n 只有树下的诗篇仍在流传\n 像一场失传已久的浪漫飘在人间\n 树上的叶绿了又黄归于尘土\n 树下的人来了又往归于尘土\n 此心已然照不见当时的明月\n 故人依然幽篁中固守着永夜\n 来来往往的人啊踏着各自的命途\n 红尘焉止是一抔可堪葬身的尘土\n 白云苍狗\n 故事从前\n 又来相见\n 今昔如花\n 不胜当年\n 月照春山\n 白云苍狗\n 故事从前\n 又来相见\n 今昔如花\n 不胜当年\n 月照春山\n 惚兮恍兮\n 此中有物\n 归于尘土\n 所谓光景\n 流年急急\n 白云一片\n la…\n 白云一片\n 枝叶招展\n 即见当年",
            "popularity": "10",
            "time": "2022-06-16T00:00:00"
        },
        {
            "song_name": "讀山海經·其一",
            "song_url": "https://music.163.com/#//song?id=1916874887",
            "lyrics": "",
            "popularity": "15",
            "time": "未找到发布日期"
        },
        {
            "song_name": "定風波",
            "song_url": "https://music.163.com/#//song?id=1916875058",
            "lyrics": "",
            "popularity": "15",
            "time": "未找到发布日期"
        },
        {
            "song_name": "偈",
            "song_url": "https://music.163.com/#//song?id=1804346407",
            "lyrics": " 作词 : 青林師虔\n 作曲 : 匡笑余\n 原诗：青林师虔·唐\n 曲/唱：匡笑余\n 中阮：邹广超\n 箫：哓哓\n 小打/录制：阿星\n 编曲：秘密后院\n 长长三尺余\n 郁郁馥芳草\n 不知何代人\n 得见此松老",
            "popularity": "27",
            "time": "2020-12-29T00:00:00"
        },
        {
            "song_name": "狂歌",
            "song_url": "https://music.163.com/#//song?id=2092752880",
            "lyrics": "",
            "popularity": "10",
            "time": "2023-10-23T00:00:00"
        }
    ]
}