{
    "id": 144,
    "singer_name": "晨曦光廊",
    "category": "华语组合/乐队",
    "singer_url": "https://music.163.com/artist?id=11318",
    "description": "演出聯繫：\nPeter\n+86 15700081007\n2750505653@qq.com\n成员：\n主吉他手：昶炀\n副吉他手：昆贤\n鼓手：允璿\n清醒时总是带着昨日未竟的功课，今日即将面对的压力，或者长久以来萦绕心头的烦恼，安慰自己：大家都一样。带着犹豫和不安，让时间压缩着，分分秒秒地流逝。作为「城市顽童」的晨㬢光廊不这么想，他们的音乐有鲜明的目标：洗涤现代人的心灵。 晨曦光廊对音色、和",
    "songs": [
        {
            "song_name": "60km/h",
            "song_url": "https://music.163.com/#//song?id=28748458",
            "lyrics": "",
            "popularity": "13649",
            "time": "2013-02-24T00:00:00"
        },
        {
            "song_name": "时间简史",
            "song_url": "https://music.163.com/#//song?id=1334297185",
            "lyrics": " 作词 : 林一谦\n 作曲 : 吴佩岭@房东的猫\n 编曲 : 晨曦光廊\n斗转星移 从你的宇宙撤离\n黎明破晓 将所有黑夜取回\n还给你引力 重置昼夜和星轨\n渴望破碎的 是眼角的一滴眼泪\n斗转星移 从你的宇宙撤离\n黎明破晓 将所有黑夜取回\n还给你引力 重置昼夜和星轨\n渴望破碎的 是眼角的一滴眼泪\n你是宇宙中最闪亮的一颗星\n我是夜空最不抒情的一滴泪\n你将星球亮起 引来 生命潮汐\n 监制：陈昶炀\n 企划统筹：李纤橙/俞绍华\n 客座鼓手：王圣展\n 贝斯：陈重玮\n 吉他：陈昶炀、林昆贤\n 合成器PG：陈昶炀\n 客座弦乐/钢琴：赖暐哲\n 录音：陈昶炀、Hao Young\n 编辑：陈昶炀\n 混音：胡俊涵\n 母带：胡俊涵",
            "popularity": "8157",
            "time": "2018-12-30T00:00:00"
        },
        {
            "song_name": "用生命写故事",
            "song_url": "https://music.163.com/#//song?id=350111",
            "lyrics": "珍惜每一分每一秒\n勇敢面對空虛與寂寥\n用生命寫的故事\n持續在吟繞 它在吟繞\n曾幾何時 我們都在逃跑\n直到失去自我 為過去哀悼\n曾幾何時 我們都在尋找\n才發現曾經擁有過的美好\n緊握著雙手\n對未來禱告\n擁抱著幸福\n不再無依無靠\n享受人生的最後一秒\n勇敢面對空虛與寂寥\n帶著勇氣 走向回憶的轉角\n帶著回憶 走向未來的軌道\n用生命寫的故事 持續在萦繞\n用生命寫的故事 持續在萦繞",
            "popularity": "2845",
            "time": "2010-04-04T00:00:00"
        },
        {
            "song_name": "小公主",
            "song_url": "https://music.163.com/#//song?id=445702011",
            "lyrics": "",
            "popularity": "2498",
            "time": "2016-12-12T00:00:00"
        },
        {
            "song_name": "风中的人",
            "song_url": "https://music.163.com/#//song?id=28748457",
            "lyrics": "詞曲/昶煬\n风中的人 风中的我\n风中的梦 看无初红\n风中的声 风中的命\n风中的窗 孤单剩啥\n雨中的歌 雨滴空梦\n雨声若响 雨落信纸\n雨中的声 雨起雨束\n雨想起我 风中的人\n异乡的我 不知畏寒\n思落心晟 捶阮心肝\n故乡的山 放阮思念\n血流花草 汗流寒冬\n红色的梦(风中的人你跑去哪裡啊)\n青天在哪(风中的人你飞去哪裡啊)\n世事说啥(风中的人你跑去哪裡啊)\n伤痕醒了(哪会给我这种感觉 我的命剩啥)\n逝去笑梦(风中的人 风中的人)\n想起亲人(风中的我 风中的我)\n讲的思念(风中的梦 风中的梦)\n风声知影(哪会给我这种感觉 我的命剩啥 剩啥)\n异乡的我 不知畏寒\n思落心晟 捶阮心肝\n故乡的山 放阮思念\n雨起雨落\n风中的人啊\n异乡的我 不知畏寒\n思落心晟 捶阮心肝\n故乡的山 放阮思念\n血流花草 汗流寒冬\n红色的梦 青天在哪\n世事说啥 伤痕醒了\n逝去笑梦 想起亲人\n讲的思念 风声知影\n风中的人 风中的我\n风中的梦 看无初红\n风中的声 风中的命\n风中的窗 孤单剩啥\n雨中的歌(雨中的歌 雨中的歌)\n雨滴空梦(雨滴空梦 雨滴空梦)\n雨声若响(雨水滴到阮的心声)\n雨落信纸(雨水滴到阮的心晟)\n雨中的声(雨中的声 雨中的声)\n雨起雨束(雨起雨束 雨起雨束)\n雨想起我(雨水亲像阮的思念)\n风中的人(送给风中的人)\n把我的故乡 还给我",
            "popularity": "863",
            "time": "2013-02-24T00:00:00"
        },
        {
            "song_name": "白纸",
            "song_url": "https://music.163.com/#//song?id=1323301402",
            "lyrics": " 作词 : 晨曦光廊\n 作曲 : 晨曦光廊\n想哩的自然 想他的一切\n放日子过啊过 后悔\n心爱的哩在刀 明知他不再回\n放时间飞啊飞 浪费\n我甘愿付出一切 换来真心的钦佩\n你笑我不曾清醒 满腹怨切\n离开那天哩共拍谢 拍谢大声共诉心内话\n写一张 乎你我青春的信\n一个人甘愿来离开 回头看甘苦心伤悲\n风吹来 就亲像叫著咱的名字\n人生路坎坷无人知 想欲哭免怕没目屎\n坚强走 提阮的青春到未来\n-solo-\n我甘愿付出一切 换来真心的钦佩\n你笑我不曾清醒 满腹怨切\n离开那天哩共拍谢 拍谢大声共诉心内话\n写一张 乎你我青春的信\n一个人甘愿来离开 回头看甘苦心伤悲\n风吹来 就亲像叫著咱的名字\n人生路坎坷无人知 想欲哭免怕没目屎\n坚强走 提阮的青春到未来\n若 听到吉他声 光照到咱的形影\n唱出心内的孤单\n卖抹记藏在心中的那张白纸\n若 听到您的声 光照到您的形影\n唱出心内的孤单\n卖抹记藏在心中的那张白纸",
            "popularity": "744",
            "time": "2018-11-13T00:00:00"
        },
        {
            "song_name": "小勇士",
            "song_url": "https://music.163.com/#//song?id=441116789",
            "lyrics": "",
            "popularity": "466",
            "time": "2016-11-21T00:00:00"
        },
        {
            "song_name": "光合作用",
            "song_url": "https://music.163.com/#//song?id=28748456",
            "lyrics": "",
            "popularity": "879",
            "time": "2013-02-24T00:00:00"
        },
        {
            "song_name": "河的孩子",
            "song_url": "https://music.163.com/#//song?id=1323304403",
            "lyrics": "",
            "popularity": "918",
            "time": "2018-11-13T00:00:00"
        },
        {
            "song_name": "人间序曲",
            "song_url": "https://music.163.com/#//song?id=445702010",
            "lyrics": "",
            "popularity": "439",
            "time": "2016-12-12T00:00:00"
        },
        {
            "song_name": "送子鸟",
            "song_url": "https://music.163.com/#//song?id=1411535891",
            "lyrics": "",
            "popularity": "247",
            "time": "2019-12-24T00:00:00"
        },
        {
            "song_name": "方尼梦",
            "song_url": "https://music.163.com/#//song?id=1323303375",
            "lyrics": " 作词 : 晨曦光廊\n 作曲 : 晨曦光廊\n用多少苦 来交换成长\n用多少眼泪 来成就坚强\n要多少恨 要多少痛\n要多少爱 除一切苦难\n用苦 去交换成长\n用眼泪 去成就坚强\n用恨 用爱\n化一切苦难 去感受到爱",
            "popularity": "270",
            "time": "2018-11-13T00:00:00"
        },
        {
            "song_name": "知义里",
            "song_url": "https://music.163.com/#//song?id=28748455",
            "lyrics": "",
            "popularity": "128",
            "time": "2013-02-24T00:00:00"
        },
        {
            "song_name": "小勇士 (新版)",
            "song_url": "https://music.163.com/#//song?id=445703011",
            "lyrics": "",
            "popularity": "418",
            "time": "2016-12-12T00:00:00"
        },
        {
            "song_name": "勾勾手",
            "song_url": "https://music.163.com/#//song?id=1411536825",
            "lyrics": "",
            "popularity": "79",
            "time": "2019-12-24T00:00:00"
        },
        {
            "song_name": "余生",
            "song_url": "https://music.163.com/#//song?id=1411536826",
            "lyrics": "",
            "popularity": "74",
            "time": "2019-12-24T00:00:00"
        },
        {
            "song_name": "正义的伙伴",
            "song_url": "https://music.163.com/#//song?id=350112",
            "lyrics": "Maybe one day  I will face death\nBut today  I coose to believe you all\nBecause one day in the future\nYou will be my source of strength\nJustice Partners\nJustice Partners\nBecause one day in the future\nYou will be my source of strength\nlast forever\nlast forever\nBecause one day in the future\nYou will be my source of strength\nlast forever\nI never regret but reality is always trying to kill my dreams\nI can not lose because we are Sun Of Morning\nI never regret\nI never regret\nI never regret cause we are Justice Partners\nI never regret\nI never regret\nYou will be my source last forever\nJustice Partners\nlast forever\n You are my Justice Partners",
            "popularity": "250",
            "time": "2010-04-04T00:00:00"
        },
        {
            "song_name": "牺牲在血泊之中",
            "song_url": "https://music.163.com/#//song?id=350113",
            "lyrics": "",
            "popularity": "227",
            "time": "2010-04-04T00:00:00"
        },
        {
            "song_name": "英雄同狂",
            "song_url": "https://music.163.com/#//song?id=1411536827",
            "lyrics": "",
            "popularity": "99",
            "time": "2019-12-24T00:00:00"
        },
        {
            "song_name": "当我们徬徨的时候",
            "song_url": "https://music.163.com/#//song?id=350109",
            "lyrics": "",
            "popularity": "411",
            "time": "2010-04-04T00:00:00"
        },
        {
            "song_name": "Forget",
            "song_url": "https://music.163.com/#//song?id=350108",
            "lyrics": "",
            "popularity": "129",
            "time": "2010-04-04T00:00:00"
        },
        {
            "song_name": "牺牲在血泊之中",
            "song_url": "https://music.163.com/#//song?id=5236637",
            "lyrics": "",
            "popularity": "11",
            "time": "2011-01-04T00:00:00"
        },
        {
            "song_name": "Cheater",
            "song_url": "https://music.163.com/#//song?id=28748454",
            "lyrics": "",
            "popularity": "117",
            "time": "2013-02-24T00:00:00"
        },
        {
            "song_name": "生命中的序曲",
            "song_url": "https://music.163.com/#//song?id=350110",
            "lyrics": "",
            "popularity": "20",
            "time": "2010-04-04T00:00:00"
        },
        {
            "song_name": "Intro",
            "song_url": "https://music.163.com/#//song?id=350107",
            "lyrics": "",
            "popularity": "101",
            "time": "2010-04-04T00:00:00"
        },
        {
            "song_name": "休息站的人们",
            "song_url": "https://music.163.com/#//song?id=1816018120",
            "lyrics": " 作词 : 福永年\n 作曲 : 陈昶炀\n把自己献给风景与艳阳\n把思绪交给时间高声唱\n带一点紧张和慌张\n期待已久的路途上\n往未知的方向\n出发\n当阳光照耀人们的脸上\n人生道路上剩谁在身旁\n力量加满我的油箱\n带着所有的行李箱\n我要更多的疯狂\n我不迷惘不徬惶不挣扎不要回头望\n你还好吗\n风雨中摇晃\n前方路障\n挡不住他\n自由就在前方\n休息站的人们呐\n转动着热情前往心之所向\n流下的每一滴汗水和每一刻善良\n都载着祝福和想像\n挥洒自己身上满载的热情送给远方\n戴上墨镜挂著毛巾挡住刺眼阳光\n搭上我们这车疯狂\n一起旅行吧\n坐着趴着跟着我们去\n好好放个假\n当阳光照耀人们的脸上\n人生道路上剩谁在身旁\n力量加满我的油箱\n带着所有的行李箱\n我要更多疯狂\n我不迷惘不徬惶不挣扎不要回头望\n你还好吗\n风雨中摇晃\n前方路障\n挡不住他\n自由就在前方\n休息站的人们呐~\n流下的每一滴汗水和每一刻善良\n载着满满的祝福和想像\n搭上我们这车疯狂\n一起旅行吧\n坐着趴着跟着我们去\n好好放个假\n把自己献给风景\n把自己献给艳阳\n把自己献给时间高声高声唱\n带一点紧张 和一点慌张\n期待已久的路途上往未知的方向出发\n当阳光照耀人们的脸上\n人生道路上剩谁剩谁还在身旁\n力量加满我的油箱\n带着所有的行李箱\n要更多的疯狂 自由就在前方\n休息站的人们啊",
            "popularity": "18",
            "time": "2021-02-03T00:00:00"
        },
        {
            "song_name": "结婚，美梦 feat.昶旸 @晨曦光廊",
            "song_url": "https://music.163.com/#//song?id=1882646488",
            "lyrics": " 作词 : 荔枝/芒果\n 作曲 : 荔枝/芒果\n 编曲 : 安娜其\n 男女相逢心相爱，营谋买卖大招财。\n 敢若（好像）做了一个有花有草的梦\n 不要惊（怕） 我的心内（心里）\n 就像是看到那个所在（地方）\n 怎会目屎（眼泪）没完没了地流\n 突然间 我的生活发生了美丽的变化\n 时间啊  不甘啊\n 放纵啊  混乱啊\n 你我的心肝 怎会不停地 为你我受伤 血流\n 遗憾的人生啊 才更加的完整啊\n 你我的心肝 怎会不停地 为你我受伤 血流\n 遗憾的人生啊 才更加的完整啊\n 哪有彼多（这么多）要死要活的缘\n 咱拢是（我们都是） 彼无细腻（这么不小心）\n 偏偏就 栽在以为的爱\n 若是知道你我头前（前面）的路\n 没期待 也别冷心（灰心）\n 这拢（都）是命运的安排\n 时间啊  不甘啊\n 放纵啊  混乱啊\n 你我的心肝 怎会不停地 为你我受伤 血流\n 遗憾的人生啊 才更加的完整啊\n 你我的心肝 怎会不停地 为你我受伤 血流\n 遗憾的人生啊 才更加的完整啊\n 一 二 三 四\n 痴痴地等\n 咱拢是（我们都是） 心中有怨叹\n 痴痴地等\n 咱拢是（我们都是） 活过这一辈子（一世人）\n 痴痴地等\n 咱拢是（我们都是） 心中有怨叹\n 痴痴地等\n 妈妈（阿母）叫你 做人 要知足 也要平安\n 主唱 Vocal及合成器Synth：荔枝\n 吉他 Guitar：芒果\n 贝斯 Bass：张向\n 主唱 Vocal：荔枝 昶旸 @晨曦光廊\n 和声 Chorus：荔枝 昶旸\n 制作 Producer ：芒果\n 编曲 Arranger：安娜其\n 鼓 Drum Arrangement：良仔 @沙漏SAALAU\n 录音 sound recording ： 芒果\n 混音 mixing：许经纶(怪兽) Veil帷幕工作室\n 母带后期处理 Mastering：许经纶(怪兽) Veil帷幕工作室\n 封面设计：高一点\n MV导演及影像后制处理：浩浩(浩工作室)\n MV台北拍摄协助：摄影师/志豪，灯光师/林威\n MV妆发：王大禹\n 艺人制作与经纪：Veil 帷幕工作室\n 宣传统筹：缪佳玮\n 经纪人：许经纶(怪兽)\n 版权声明：未经著作权人书面许可，任何人不得以任何方式使用（包括翻唱、翻录等）",
            "popularity": "15",
            "time": "2021-10-09T00:00:00"
        },
        {
            "song_name": "结婚，美梦",
            "song_url": "https://music.163.com/#//song?id=1893279650",
            "lyrics": " 作词 : 荔枝/芒果\n 作曲 : 荔枝/芒果\n 编曲 : 安娜其\n           男女相逢心相爱，营谋买卖大招财。        （摘自和合二仙秘咒）\n敢若（好像）做了一个有花有草的梦\n不要惊（怕） 我的心内（心里）\n就像是看到那个所在（地方）\n怎会目屎（眼泪）没完没了地流\n突然间 我的生活发生了美丽的变化\n时间啊  不甘啊\n放纵啊  混乱啊\n你我的心肝 怎会不停地 为你我受伤 血流\n遗憾的人生啊 才更加的完整啊\n你我的心肝 怎会不停地 为你我受伤 血流\n遗憾的人生啊 才更加的完整啊\n哪有彼多（这么多）要死要活的缘\n咱拢是（我们都是） 彼无细腻（这么不小心）\n偏偏就 栽在以为的爱\n若是知道你我头前（前面）的路\n没期待 也别冷心（灰心）\n这拢（都）是命运的安排\n时间啊  不甘啊\n放纵啊  混乱啊\n你我的心肝 怎会不停地 为你我受伤 血流\n遗憾的人生啊 才更加的完整啊\n你我的心肝 怎会不停地 为你我受伤 血流\n遗憾的人生啊 才更加的完整啊\n一 二 三 四\n痴痴地等\n咱拢是（我们都是） 心中有怨叹\n痴痴地等\n咱拢是（我们都是） 活过这一辈子（一世人）\n痴痴地等\n咱拢是（我们都是） 心中有怨叹\n痴痴地等\n妈妈（阿母）叫你 做人 要知足 也要平安\n 乐队成员：\n 主唱 Vocal及合成器Synth：荔枝\n 吉他 Guitar：芒果\n 贝斯 Bass：张向\n 主唱 Vocal：荔枝 昶旸 @晨曦光廊\n 和声 Chorus：荔枝 昶旸\n 制作 Producer ：芒果\n 编曲 Arranger：安娜其\n 鼓 Drum Arrangement：良仔 @沙漏SAALAU\n 录音 sound recording ： 芒果\n 混音 mixing：许经纶(怪兽) Veil帷幕工作室\n 母带后期处理 Mastering：许经纶(怪兽) Veil帷幕工作室\n 封面设计：高一点\n MV导演及影像后制处理：浩浩(浩工作室)\n MV台北拍摄协助：摄影师/志豪，灯光师/林威\n MV妆发：王大禹\n 艺人制作与经纪：Veil 帷幕工作室\n 宣传统筹：缪佳玮\n 经纪人：许经纶(怪兽)\n 版权声明：未经著作权人书面许可，任何人不得以任何方式使用（包括翻唱、翻录等）",
            "popularity": "24",
            "time": "未找到发布日期"
        },
        {
            "song_name": "小公主",
            "song_url": "https://music.163.com/#//song?id=516234033",
            "lyrics": "",
            "popularity": "29",
            "time": "2017-11-03T00:00:00"
        }
    ]
}